starlette_cramjam/__init__.py
starlette_cramjam/compression.py
starlette_cramjam/middleware.py
starlette_cramjam-0.5.0.dist-info/licenses/LICENSE
starlette_cramjam-0.5.0.dist-info/WHEEL
starlette_cramjam-0.5.0.dist-info/METADATA
starlette_cramjam-0.5.0.dist-info/RECORD
