Metadata-Version: 2.4
Name: starlette-cramjam
Version: 0.5.0
Summary: Cramjam integration for Starlette ASGI framework.
Keywords: Cramjam,Compression,ASGI,Starlette
Author-email: Vincent Sarago <vincent@developmentseed.com>
Requires-Python: >=3.7
Classifier: Intended Audience :: Information Technology
Classifier: Intended Audience :: Science/Research
Classifier: License :: OSI Approved :: MIT License
Classifier: Programming Language :: Python :: 3.9
Classifier: Programming Language :: Python :: 3.10
Classifier: Programming Language :: Python :: 3.11
Classifier: Programming Language :: Python :: 3.12
Classifier: Programming Language :: Python :: 3.13
Classifier: Typing :: Typed
License-File: LICENSE
Requires-Dist: starlette
Requires-Dist: cramjam>=2.4,<2.11
Requires-Dist: pre-commit ; extra == "dev"
Requires-Dist: bump-my-version ; extra == "dev"
Requires-Dist: pytest ; extra == "test"
Requires-Dist: pytest-cov ; extra == "test"
Requires-Dist: httpx ; extra == "test"
Requires-Dist: brotlipy ; extra == "test"
Requires-Dist: zstandard ; extra == "test"
Project-URL: Source, https://github.com/developmentseed/starlette-cramjam
Provides-Extra: dev
Provides-Extra: test
